py_ecowater/__init__.py
py_ecowater/constants.py
py_ecowater/ecowater_client.py
py_ecowater/exception.py
py_ecowater/model.py
py_ecowater-0.1.3.dist-info/LICENSE
py_ecowater-0.1.3.dist-info/METADATA
py_ecowater-0.1.3.dist-info/WHEEL
py_ecowater-0.1.3.dist-info/top_level.txt
py_ecowater-0.1.3.dist-info/RECORD
