Metadata-Version: 2.1
Name: py-ecowater
Version: 0.1.3
Summary: A python package for interacting with the Ecowater API
Home-page: https://github.com/ejsuncy/py_ecowater
Author: Dan Bunker
Author-email: dbunked@gmail.com
Project-URL: Bug Tracker, https://github.com/ejsuncy/py_ecowater/issues
Classifier: Programming Language :: Python :: 3
Classifier: License :: OSI Approved :: MIT License
Classifier: Operating System :: OS Independent
Requires-Python: >=3.8
License-File: LICENSE
